mergen/__init__.py
mergen/main.py
mergen-1.0.dist-info/LICENSE
mergen-1.0.dist-info/METADATA
mergen-1.0.dist-info/WHEEL
mergen-1.0.dist-info/top_level.txt
mergen-1.0.dist-info/RECORD
