Metadata-Version: 2.1
Name: mergen
Version: 1.0
Summary: Unsupervised learning using data in time-domain astronomy
Home-page: https://github.com/tdaylan/mergen
Author: Tansu Daylan, Emma Chickles, and Lindsey Gordon
Author-email: tansu.daylan@gmail.com
License: MIT
Download-URL: https://github.com/tdaylan/mergen
Platform: UNKNOWN
Classifier: Development Status :: 4 - Beta
Classifier: Intended Audience :: Science/Research
Classifier: License :: OSI Approved :: MIT License
Classifier: Programming Language :: Python
